odoo/addons/cooperator_portal/README.rst
odoo/addons/cooperator_portal/__init__.py
odoo/addons/cooperator_portal/__manifest__.py
odoo/addons/cooperator_portal/controllers/__init__.py
odoo/addons/cooperator_portal/controllers/portal.py
odoo/addons/cooperator_portal/i18n/cooperator_portal.pot
odoo/addons/cooperator_portal/i18n/fr.po
odoo/addons/cooperator_portal/i18n/fr_BE.po
odoo/addons/cooperator_portal/i18n/it.po
odoo/addons/cooperator_portal/models/__init__.py
odoo/addons/cooperator_portal/models/res_partner.py
odoo/addons/cooperator_portal/readme/CONTRIBUTORS.rst
odoo/addons/cooperator_portal/readme/DESCRIPTION.rst
odoo/addons/cooperator_portal/readme/ROADMAP.rst
odoo/addons/cooperator_portal/static/description/icon.png
odoo/addons/cooperator_portal/static/description/index.html
odoo/addons/cooperator_portal/views/portal_templates.xml
odoo14_addon_cooperator_portal-14.0.1.0.2.dist-info/METADATA
odoo14_addon_cooperator_portal-14.0.1.0.2.dist-info/WHEEL
odoo14_addon_cooperator_portal-14.0.1.0.2.dist-info/top_level.txt
odoo14_addon_cooperator_portal-14.0.1.0.2.dist-info/RECORD
